TeenStudy/__init__.py
TeenStudy/models/__init__.py
TeenStudy/models/accuont.py
TeenStudy/models/dxx.py
TeenStudy/resource/MiSans-Light.ttf
TeenStudy/resource/answer.png
TeenStudy/resource/backgroud1.jpg
TeenStudy/resource/backgroud2.jpg
TeenStudy/resource/backgroud3.jpg
TeenStudy/resource/backgroud4.jpg
TeenStudy/resource/backgroud5.jpg
TeenStudy/utils/__init__.py
TeenStudy/utils/dxx.py
TeenStudy/utils/handle.py
TeenStudy/utils/path.py
TeenStudy/utils/rule.py
TeenStudy/utils/update.py
TeenStudy/utils/utils.py
TeenStudy/web/__init__.py
TeenStudy/web/api/__init__.py
TeenStudy/web/api/add.py
TeenStudy/web/api/admin.py
TeenStudy/web/api/home.py
TeenStudy/web/api/log.py
TeenStudy/web/api/login.py
TeenStudy/web/pages/__init__.py
TeenStudy/web/pages/add.py
TeenStudy/web/pages/addArea.py
TeenStudy/web/pages/admin.py
TeenStudy/web/pages/home.py
TeenStudy/web/pages/log.py
TeenStudy/web/pages/login.py
TeenStudy/web/utils/__init__.py
TeenStudy/web/utils/add.py
TeenStudy/web/utils/status.py
teenstudy-0.2.6.dist-info/LICENSE
teenstudy-0.2.6.dist-info/METADATA
teenstudy-0.2.6.dist-info/WHEEL
teenstudy-0.2.6.dist-info/RECORD
