Metadata-Version: 2.1
Name: TeenStudy
Version: 0.2.6
Summary: 基于nonebot2的青年大学习自动提交插件，用于自动完成大学习，在后台留下记录，返回完成截图
Home-page: https://github.com/YouthLearning/TeenStudy
License: MIT
Author: TeenStudyFlow
Author-email: TeenStudyFlow@gmail.com
Requires-Python: >=3.8,<4.0
Classifier: License :: OSI Approved :: MIT License
Classifier: Programming Language :: Python :: 3
Classifier: Programming Language :: Python :: 3.8
Classifier: Programming Language :: Python :: 3.9
Classifier: Programming Language :: Python :: 3.10
Classifier: Programming Language :: Python :: 3.11
Classifier: Programming Language :: Python :: 3.12
Requires-Dist: Jinja2 (>=3.1.2,<4.0.0)
Requires-Dist: amis-python (>=1.0.8,<2.0.0)
Requires-Dist: anti-useragent (>=1.0.10,<2.0.0)
Requires-Dist: beautifulsoup4 (>=4.11.2,<5.0.0)
Requires-Dist: bs4 (>=0.0.1,<0.0.2)
Requires-Dist: ddddocr (>=1.4.7,<2.0.0)
Requires-Dist: fastapi (>=0.100.0,<0.101.0)
Requires-Dist: httpx (>=0.24.0,<0.25.0)
Requires-Dist: lxml (>=4.9.2,<5.0.0)
Requires-Dist: nonebot-adapter-onebot (>=2.2.3,<3.0.0)
Requires-Dist: nonebot-plugin-apscheduler (>=0.3.0,<0.4.0)
Requires-Dist: nonebot2 (>=2.0.0,<3.0.0)
Requires-Dist: psutil (>=5.9.4,<6.0.0)
Requires-Dist: pycryptodome (>=3.17,<4.0)
Requires-Dist: python-jose (>=3.3.0,<4.0.0)
Requires-Dist: qrcode (>=7.4.2,<8.0.0)
Requires-Dist: tortoise-orm (>=0.19.3,<0.20.0)
Requires-Dist: ujson (>=5.7.0,<6.0.0)
Requires-Dist: uvicorn (>=0.21.0,<0.22.0)
